adaptivepca/__init__.py
adaptivepca/adaptive_pca.py
adaptivepca-1.1.3.dist-info/LICENSE
adaptivepca-1.1.3.dist-info/METADATA
adaptivepca-1.1.3.dist-info/WHEEL
adaptivepca-1.1.3.dist-info/top_level.txt
adaptivepca-1.1.3.dist-info/RECORD
