Metadata-Version: 2.1
Name: adaptivepca
Version: 1.1.3
Summary: An advanced PCA implementation with adaptive feature scaling and preprocessing
Home-page: https://github.com/nqmn/adaptivepca
Author: Mohd Adil
Author-email: mohdadil@live.com
Keywords: machine learning,dimensionality reduction,pca,feature selection,data preprocessing,adaptive scaling,classification,data analysis,statistics
Classifier: Programming Language :: Python :: 3
Classifier: License :: OSI Approved :: MIT License
Classifier: Operating System :: OS Independent
Classifier: Topic :: Scientific/Engineering
Classifier: Topic :: Scientific/Engineering :: Artificial Intelligence
Classifier: Topic :: Software Development :: Libraries :: Python Modules
Requires-Python: >=3.8
License-File: LICENSE
Requires-Dist: numpy>=1.20.0
Requires-Dist: pandas>=1.3.0
Requires-Dist: scikit-learn>=1.0.0
Requires-Dist: scipy>=1.7.0
Requires-Dist: lightgbm>=3.3.0
Requires-Dist: imbalanced-learn>=0.8.0
